libs_gds/__init__.py
libs_gds/tes.py
libs_gds/tiktok_biasa.py
libs_gds/dist/__init__.py
libs_gds/dist/tes.py
libs_gds/dist/tiktok_biasa.py
libs_gds/dist/pytransform/__init__.py
tes_gan-0.0.1.dist-info/LICENSE
tes_gan-0.0.1.dist-info/METADATA
tes_gan-0.0.1.dist-info/WHEEL
tes_gan-0.0.1.dist-info/top_level.txt
tes_gan-0.0.1.dist-info/RECORD
