Metadata-Version: 2.1
Name: tes-gan
Version: 0.0.1
Summary: A small example package
Home-page: https://github.com/pypa/sampleproject
Author: tes_gan
Author-email: dki.hadihermawan@gmail.com
Project-URL: Bug Tracker, https://github.com/pypa/sampleproject/issues
Classifier: Programming Language :: Python :: 3
Classifier: License :: OSI Approved :: MIT License
Classifier: Operating System :: OS Independent
Requires-Python: >=3.6
License-File: LICENSE
